prometeo/__init__.py
prometeo/__main__.py
prometeo/auxl/__init__.py
prometeo/auxl/plist.py
prometeo/cgen/__init__.py
prometeo/cgen/code_gen.py
prometeo/cgen/code_gen_c.py
prometeo/cgen/node_util.py
prometeo/cgen/op_util.py
prometeo/cgen/source_repr.py
prometeo/cgen/string_repr.py
prometeo/cmdline/__init__.py
prometeo/cmdline/pmt.py
prometeo/include/blasfeo/blasfeo.h
prometeo/include/blasfeo/blasfeo_block_size.h
prometeo/include/blasfeo/blasfeo_common.h
prometeo/include/blasfeo/blasfeo_d_aux.h
prometeo/include/blasfeo/blasfeo_d_aux_ext_dep.h
prometeo/include/blasfeo/blasfeo_d_aux_ext_dep_ref.h
prometeo/include/blasfeo/blasfeo_d_aux_old.h
prometeo/include/blasfeo/blasfeo_d_aux_ref.h
prometeo/include/blasfeo/blasfeo_d_aux_test.h
prometeo/include/blasfeo/blasfeo_d_blas.h
prometeo/include/blasfeo/blasfeo_d_blas_api.h
prometeo/include/blasfeo/blasfeo_d_blasfeo_api.h
prometeo/include/blasfeo/blasfeo_d_blasfeo_api_ref.h
prometeo/include/blasfeo/blasfeo_d_kernel.h
prometeo/include/blasfeo/blasfeo_i_aux_ext_dep.h
prometeo/include/blasfeo/blasfeo_m_aux.h
prometeo/include/blasfeo/blasfeo_naming.h
prometeo/include/blasfeo/blasfeo_s_aux.h
prometeo/include/blasfeo/blasfeo_s_aux_ext_dep.h
prometeo/include/blasfeo/blasfeo_s_aux_ext_dep_ref.h
prometeo/include/blasfeo/blasfeo_s_aux_old.h
prometeo/include/blasfeo/blasfeo_s_aux_ref.h
prometeo/include/blasfeo/blasfeo_s_aux_test.h
prometeo/include/blasfeo/blasfeo_s_blas.h
prometeo/include/blasfeo/blasfeo_s_blas_api.h
prometeo/include/blasfeo/blasfeo_s_blasfeo_api.h
prometeo/include/blasfeo/blasfeo_s_blasfeo_api_ref.h
prometeo/include/blasfeo/blasfeo_s_kernel.h
prometeo/include/blasfeo/blasfeo_stdlib.h
prometeo/include/blasfeo/blasfeo_target.h
prometeo/include/blasfeo/blasfeo_timing.h
prometeo/include/blasfeo/blasfeo_v_aux_ext_dep.h
prometeo/include/blasfeo/d_blas.h
prometeo/include/blasfeo/d_blas_64.h
prometeo/include/blasfeo/s_blas.h
prometeo/include/blasfeo/s_blas_64.h
prometeo/include/prometeo/pmat_blasfeo_wrapper.h
prometeo_dsl-0.0.2.dist-info/METADATA
prometeo_dsl-0.0.2.dist-info/WHEEL
prometeo_dsl-0.0.2.dist-info/entry_points.txt
prometeo_dsl-0.0.2.dist-info/top_level.txt
prometeo_dsl-0.0.2.dist-info/RECORD
