Metadata-Version: 2.1
Name: prometeo-dsl
Version: 0.0.2
Summary: Python-to-C transpiler and domain specific language for embedded high-performance computing
Home-page: http://github.com/zanellia/prometeo
Author: Andrea Zanelli
License: LGPL
Platform: UNKNOWN
Requires-Python: >=3.6, <=3.9
Requires-Dist: astpretty
Requires-Dist: strip-hints
Requires-Dist: astunparse
Requires-Dist: numpy
Requires-Dist: scipy
Requires-Dist: multipledispatch
Requires-Dist: pyparsing
Requires-Dist: casadi (==3.4.5)
Requires-Dist: jinja2
